[
  {
    "id": 1,
    "url": "https://images.unsplash.com/photo-1540575467063-178a50c2df87?w=800&q=80",
    "caption": "ACM Launchpad 2026"
  },
  {
    "id": 2,
    "url": "https://images.unsplash.com/photo-1505373877841-8d25f7d46678?w=800&q=80",
    "caption": "Codestorm Hackathon"
  },
  {
    "id": 3,
    "url": "https://images.unsplash.com/photo-1515187029135-18ee286d815b?w=800&q=80",
    "caption": "AI Battle Finals"
  },
  {
    "id": 4,
    "url": "https://images.unsplash.com/photo-1531482615713-2afd69097998?w=800&q=80",
    "caption": "Redesignx Workshop"
  },
  {
    "id": 5,
    "url": "https://images.unsplash.com/photo-1556761175-5973dc0f32d7?w=800&q=80",
    "caption": "Web Dev Bootcamp"
  },
  {
    "id": 6,
    "url": "https://images.unsplash.com/photo-1522071820081-009f0129c71c?w=800&q=80",
    "caption": "Team Brainstorming"
  },
  {
    "id": 7,
    "url": "https://images.unsplash.com/photo-1517245386807-bb43f82c33c4?w=800&q=80",
    "caption": "Guest Lecture"
  },
  {
    "id": 8,
    "url": "https://images.unsplash.com/photo-1523240795612-9a054b0db644?w=800&q=80",
    "caption": "Student Interaction"
  },
  {
    "id": 9,
    "url": "https://images.unsplash.com/photo-1475721025505-231012bb04ff?w=800&q=80",
    "caption": "Tech Talk Session"
  },
  {
    "id": 10,
    "url": "https://images.unsplash.com/photo-1552664730-d307ca884978?w=800&q=80",
    "caption": "Project Presentations"
  },
  {
    "id": 11,
    "url": "https://images.unsplash.com/photo-1558402529-d2638a7023e9?w=800&q=80",
    "caption": "Hackathon Midnight"
  },
  {
    "id": 12,
    "url": "https://images.unsplash.com/photo-1523908511403-7fc7b25592f4?w=800&q=80",
    "caption": "Networking Break"
  },
  {
    "id": 13,
    "url": "https://images.unsplash.com/photo-1560523159-4a9692d222f9?w=800&q=80",
    "caption": "Award Ceremony"
  },
  {
    "id": 14,
    "url": "https://images.unsplash.com/photo-1504384308090-c894fdcc538d?w=800&q=80",
    "caption": "Code Review"
  },
  {
    "id": 15,
    "url": "https://images.unsplash.com/photo-1531496730074-83b638c0a7ac?w=800&q=80",
    "caption": "ACM Core Team"
  }
]
